DataMakeCN/__init__.py
DataMakeCN/datamaker.py
DataMakeCN/new_family.txt
DataMakeCN/new_names.txt
DataMakeCN/pd_datamaker.py
DataMakeCN/upgrade_log.log
mysql_study_datamaker_cn-0.2.2.1.dist-info/licenses/LICENSE
mysql_study_datamaker_cn-0.2.2.1.dist-info/METADATA
mysql_study_datamaker_cn-0.2.2.1.dist-info/WHEEL
mysql_study_datamaker_cn-0.2.2.1.dist-info/top_level.txt
mysql_study_datamaker_cn-0.2.2.1.dist-info/RECORD
