Metadata-Version: 2.4
Name: mysql_study_datamaker_CN
Version: 0.2.2.1
Summary: Generate some data and convert it to MySQL language.
Author-email: Kavin <scratch_test@126.com>
Classifier: Programming Language :: Python :: 3
Classifier: License :: OSI Approved :: MIT License
Classifier: Operating System :: OS Independent
Requires-Python: >=3.8
License-File: LICENSE
Dynamic: license-file
